[
    {
        "nodes": [
            {
                "id": 0,
                "content": "A",
                "type": "input port"
            },
            {
                "id": 1,
                "content": "B",
                "type": "input port"
            },
            {
                "id": 2,
                "content": "result",
                "type": "output port"
            },
            {
                "id": 3,
                "content": "odd",
                "type": "output port"
            },
            {
                "id": 4,
                "content": "ctrl",
                "type": "submodule"
            }
        ],
        "edge_attrs": [],
        "connectivity": [
            [
                1,
                0,
                4,
                4
            ],
            [
                4,
                4,
                2,
                3
            ]
        ]
    }
]