{
    "type": "module_graph",
    "edge_attrs": [],
    "has_edge_features": false,
    "nodes": [
        {
            "id": 0,
            "content": "clk",
            "type": "input port"
        },
        {
            "id": 1,
            "content": "a",
            "type": "input port"
        },
        {
            "id": 2,
            "content": "b",
            "type": "input port"
        },
        {
            "id": 3,
            "content": "op_sel",
            "type": "input port"
        },
        {
            "id": 4,
            "content": "result",
            "type": "output port"
        },
        {
            "id": 5,
            "content": "u_adder",
            "type": "submodule"
        },
        {
            "id": 6,
            "content": "u_subtractor",
            "type": "submodule"
        },
        {
            "id": 7,
            "content": "u_and",
            "type": "submodule"
        },
        {
            "id": 8,
            "content": "u_or",
            "type": "submodule"
        }
    ],
    "connectivity": [
        [
            1,
            2,
            1,
            2,
            1,
            2,
            1,
            2,
            7,
            6,
            8,
            5
        ],
        [
            5,
            5,
            6,
            6,
            7,
            7,
            8,
            8,
            4,
            4,
            4,
            4
        ]
    ]
}